metrist/__init__.py
metrist_agent_canmonuser-0.0.1.dist-info/METADATA
metrist_agent_canmonuser-0.0.1.dist-info/WHEEL
metrist_agent_canmonuser-0.0.1.dist-info/licenses/LICENSE
metrist_agent_canmonuser-0.0.1.dist-info/RECORD
