Metadata-Version: 2.1
Name: metrist_agent_canmonuser
Version: 0.0.1
Summary: Metrist In-Process Agent
Author-email: "Metrist Software, Inc." <support@metrist.io>
License-File: LICENSE
Classifier: Operating System :: OS Independent
Classifier: Programming Language :: Python :: 3
Requires-Python: >=3.7
